rechip8/__main__.py
rechip8/bin/FONT
rechip8/bin/ibm.ch8
rechip8/core/__init__.py
rechip8/core/constants.py
rechip8/core/cpu.py
rechip8/core/display.py
rechip8/core/keypad.py
rechip8/core/memory.py
rechip8/core/opcode.py
rechip8/static/beep.mp3
rechip8/static/invader.png
rechip8-1.4.3.dist-info/LICENSE
rechip8-1.4.3.dist-info/WHEEL
rechip8-1.4.3.dist-info/METADATA
rechip8-1.4.3.dist-info/RECORD
